pstyle/__init__.py
pstyle/convert.py
pstyle/load_drivers.py
pstyle/main.py
pstyle/version.py
pstyle/wrapper.py
pstyle-0.2.dist-info/LICENSE
pstyle-0.2.dist-info/METADATA
pstyle-0.2.dist-info/WHEEL
pstyle-0.2.dist-info/entry_points.txt
pstyle-0.2.dist-info/top_level.txt
pstyle-0.2.dist-info/zip-safe
pstyle-0.2.dist-info/RECORD
