Metadata-Version: 2.1
Name: pstyle
Version: 0.2
Summary: python DB-API paramstyle converter
Home-page: https://github.com/wtnb75/pstyle
Author: Watanabe Takashi
Author-email: wtnb75@gmail.com
License: MIT
Classifier: Development Status :: 3 - Alpha
Classifier: Intended Audience :: Developers
Classifier: License :: OSI Approved :: MIT License
Classifier: Topic :: Documentation
Classifier: Programming Language :: Python :: 3
License-File: LICENSE
Requires-Dist: click
Requires-Dist: sqlparse
Provides-Extra: drivers
Requires-Dist: duckdb ; extra == 'drivers'
Requires-Dist: firebird-driver ; extra == 'drivers'
Requires-Dist: mysql-connector-python ; extra == 'drivers'
Requires-Dist: oracledb ; extra == 'drivers'
Requires-Dist: psycopg2-binary ; extra == 'drivers'
Requires-Dist: py-postgresql ; extra == 'drivers'
Requires-Dist: pydrda ; extra == 'drivers'
Requires-Dist: pymonetdb ; extra == 'drivers'
Requires-Dist: pymssql ; extra == 'drivers'
Requires-Dist: pyodbc ; extra == 'drivers'
Requires-Dist: pyhive ; extra == 'drivers'
Requires-Dist: ipython ; extra == 'drivers'
